{
    "profiles": [
        {
            "complex_modifications": {
                "rules": [
                    {
                        "description": "Use left shift to Change to/from English input.",
                        "enabled": false,
                        "manipulators": [
                            {
                                "from": { "key_code": "left_shift" },
                                "to": [{ "key_code": "left_shift" }],
                                "to_if_alone": [{ "key_code": "fn" }],
                                "type": "basic"
                            }
                        ]
                    },
                    {
                        "description": "Tab mode",
                        "manipulators": [
                            {
                                "conditions": [
                                    {
                                        "name": "tab_mode",
                                        "type": "variable_if",
                                        "value": 1
                                    }
                                ],
                                "description": "m: Mail",
                                "from": {
                                    "key_code": "m",
                                    "modifiers": { "optional": ["any"] }
                                },
                                "to": [{ "shell_command": "open -a 'Mail.app'" }],
                                "type": "basic"
                            },
                            {
                                "conditions": [
                                    {
                                        "name": "tab_mode",
                                        "type": "variable_if",
                                        "value": 1
                                    }
                                ],
                                "description": "e: Editor",
                                "from": {
                                    "key_code": "e",
                                    "modifiers": { "optional": ["any"] }
                                },
                                "to": [{ "shell_command": "open -a 'Alacritty'" }],
                                "type": "basic"
                            },
                            {
                                "conditions": [
                                    {
                                        "name": "tab_mode",
                                        "type": "variable_if",
                                        "value": 1
                                    }
                                ],
                                "description": "w: Zen",
                                "from": {
                                    "key_code": "w",
                                    "modifiers": { "optional": ["any"] }
                                },
                                "to": [{ "shell_command": "open -a 'Zen'" }],
                                "type": "basic"
                            },
                            {
                                "conditions": [
                                    {
                                        "name": "tab_mode",
                                        "type": "variable_if",
                                        "value": 1
                                    }
                                ],
                                "description": "c: Chrome",
                                "from": {
                                    "key_code": "c",
                                    "modifiers": { "optional": ["any"] }
                                },
                                "to": [{ "shell_command": "open -a 'Google Chrome'" }],
                                "type": "basic"
                            },
                            {
                                "conditions": [
                                    {
                                        "name": "tab_mode",
                                        "type": "variable_if",
                                        "value": 1
                                    }
                                ],
                                "description": "h -> Left Arrow",
                                "from": {
                                    "key_code": "h",
                                    "modifiers": { "optional": ["any"] }
                                },
                                "to": [{ "key_code": "left_arrow" }],
                                "type": "basic"
                            },
                            {
                                "conditions": [
                                    {
                                        "name": "tab_mode",
                                        "type": "variable_if",
                                        "value": 1
                                    }
                                ],
                                "description": "j -> Down Arrow",
                                "from": {
                                    "key_code": "j",
                                    "modifiers": { "optional": ["any"] }
                                },
                                "to": [{ "key_code": "down_arrow" }],
                                "type": "basic"
                            },
                            {
                                "conditions": [
                                    {
                                        "name": "tab_mode",
                                        "type": "variable_if",
                                        "value": 1
                                    }
                                ],
                                "description": "k -> Up Arrow",
                                "from": {
                                    "key_code": "k",
                                    "modifiers": { "optional": ["any"] }
                                },
                                "to": [{ "key_code": "up_arrow" }],
                                "type": "basic"
                            },
                            {
                                "conditions": [
                                    {
                                        "name": "tab_mode",
                                        "type": "variable_if",
                                        "value": 1
                                    }
                                ],
                                "description": "l -> Right Arrow",
                                "from": {
                                    "key_code": "l",
                                    "modifiers": { "optional": ["any"] }
                                },
                                "to": [{ "key_code": "right_arrow" }],
                                "type": "basic"
                            },
                            {
                                "description": "Tab key: Hold to enable 'tab_mode', tap for Tab",
                                "from": {
                                    "key_code": "tab",
                                    "modifiers": { "optional": ["shift", "control", "option"] }
                                },
                                "to": [
                                    {
                                        "set_variable": {
                                            "name": "tab_mode",
                                            "value": 1
                                        }
                                    }
                                ],
                                "to_after_key_up": [
                                    {
                                        "set_variable": {
                                            "name": "tab_mode",
                                            "value": 0
                                        }
                                    }
                                ],
                                "to_if_alone": [{ "key_code": "tab" }],
                                "type": "basic"
                            }
                        ]
                    },
                    {
                        "description": "Left Control -> Control when held, Escape when tapped",
                        "manipulators": [
                            {
                                "from": {
                                    "key_code": "left_control",
                                    "modifiers": { "optional": ["any"] }
                                },
                                "parameters": { "basic.to_if_alone_timeout_milliseconds": 200 },
                                "to": [{ "key_code": "left_control" }],
                                "to_if_alone": [{ "key_code": "escape" }],
                                "type": "basic"
                            }
                        ]
                    }
                ]
            },
            "devices": [
                {
                    "identifiers": { "is_keyboard": true },
                    "simple_modifications": [
                        {
                            "from": { "key_code": "caps_lock" },
                            "to": [{ "key_code": "left_control" }]
                        }
                    ]
                },
                {
                    "identifiers": {
                        "is_keyboard": true,
                        "product_id": 641,
                        "vendor_id": 1452
                    },
                    "simple_modifications": [
                        {
                            "from": { "key_code": "caps_lock" },
                            "to": [{ "key_code": "left_control" }]
                        }
                    ]
                }
            ],
            "name": "Default profile",
            "selected": true,
            "simple_modifications": [
                {
                    "from": { "key_code": "right_command" },
                    "to": [{ "apple_vendor_top_case_key_code": "keyboard_fn" }]
                }
            ],
            "virtual_hid_keyboard": { "keyboard_type_v2": "ansi" }
        }
    ]
}